addispayweb/__init__.py
addispayweb/addispay.py
addispayweb/test.py
addispayweb/utils.py
addispayweb-0.1.0.dist-info/LICENSE
addispayweb-0.1.0.dist-info/METADATA
addispayweb-0.1.0.dist-info/WHEEL
addispayweb-0.1.0.dist-info/top_level.txt
addispayweb-0.1.0.dist-info/RECORD
