Metadata-Version: 2.1
Name: addispayweb
Version: 0.1.0
Summary: Python package used to integrate Addispay web API
Home-page: https://github.com/AddisPay/AddisPayPythonPackage
Download-URL: https://github.com/AddisPay/AddisPayPythonPackage/archive/refs/heads/main.zip
Author: AddisPay
Author-email: admin@bizfyspot.com
License: MIT
Classifier: Development Status :: 3 - Alpha
Classifier: Intended Audience :: Developers
Classifier: Topic :: Software Development :: Build Tools
Classifier: License :: OSI Approved :: MIT License
Classifier: Programming Language :: Python :: 3
Classifier: Programming Language :: Python :: 3.3
Classifier: Programming Language :: Python :: 3.4
Classifier: Programming Language :: Python :: 3.5
Classifier: Programming Language :: Python :: 3.6
Classifier: Programming Language :: Python :: 3.7
Classifier: Programming Language :: Python :: 3.8
Classifier: Programming Language :: Python :: 3.9
Classifier: Programming Language :: Python :: 3.10
Classifier: Programming Language :: Python :: 3.11
License-File: LICENSE
Requires-Dist: pycryptodome
Requires-Dist: requests
Requires-Dist: rsa
Requires-Dist: six
